{
  "fetch_state": {
    "howell": {
      "last_fetch_date": "2026-03-18",
      "last_content_id": "https://capitalwars.substack.com/p/global-liquidity-watch-weekly-update-9f9",
      "last_content_date": "2026-03-17"
    },
    "lyn_alden": {
      "last_fetch_date": "2026-03-16",
      "last_content_id": "https://www.lynalden.com/the-stolguard-incident/",
      "last_content_date": "2026-03-13"
    },
    "forward_guidance": {
      "last_fetch_date": "2026-03-13",
      "last_content_id": "frhd5xHQ_5Y",
      "last_content_date": "2026-03-13"
    },
    "macro_alf": {
      "last_fetch_date": "2026-03-10",
      "last_content_id": "https://themacrocompass.substack.com/p/all-you-need-to-know-about-warsh",
      "last_content_date": "2026-02-10"
    },
    "hussman": {
      "last_fetch_date": "2026-03-16",
      "last_content_id": "https://www.hussmanfunds.com/comment/mc260314/",
      "last_content_date": "2026-03-13"
    },
    "doomberg": {
      "last_fetch_date": "2026-03-20",
      "last_content_id": "https://newsletter.doomberg.com/p/project-turtle",
      "last_content_date": "2026-03-19"
    },
    "crescat": {
      "last_fetch_date": "2026-03-16",
      "last_content_id": "btr4WRySNFs",
      "last_content_date": "2026-03-14"
    },
    "zerohedge": {
      "last_fetch_date": "2026-03-20",
      "last_content_id": "https://www.zerohedge.com/markets/out-bdc-clo-worlds-largest-private-credit-fund-repacking-loans-bonds-hoping-find-new",
      "last_content_date": "2026-03-20"
    },
    "damped_spring": {
      "last_fetch_date": "2026-03-10",
      "last_content_id": "8H4S99phi38",
      "last_content_date": "2026-02-13"
    },
    "hidden_forces": {
      "last_fetch_date": "2026-03-17",
      "last_content_id": "Iu0YtkOmX2Y",
      "last_content_date": "2026-03-16"
    },
    "luke_gromen": {
      "last_fetch_date": "2026-03-11",
      "last_content_id": "lSGP4nbh9Cc",
      "last_content_date": "2026-03-10"
    },
    "jeff_snider": {
      "last_fetch_date": "2026-03-17",
      "last_content_id": "tuE_WGSQGLU",
      "last_content_date": "2026-03-16"
    },
    "lyn_alden_yt": {
      "last_fetch_date": "2026-03-10",
      "last_content_id": "jk_HWmmwiAs",
      "last_content_date": "2024-04-28"
    }
  },
  "last_updated": "2026-03-20"
}